setup.py
arena/__init__.py
arena/auth.py
arena/blocks.py
arena/channels.py
arena/feed.py
arena/resource.py
arena/search.py
arena/users.py
arena.egg-info/PKG-INFO
arena.egg-info/SOURCES.txt
arena.egg-info/dependency_links.txt
arena.egg-info/requires.txt
arena.egg-info/top_level.txt
tests/__init__.py
tests/block_tests.py
tests/channel_tests.py
tests/user_tests.py