Metadata-Version: 1.0
Name: arena
Version: 0.0.5
Summary: python interface to the are.na api
Home-page: https://github.com/frnsys/arena
Author: Francis Tseng (@frnsys)
Author-email: UNKNOWN
License: MIT
Platform: UNKNOWN
